kubragen2/__init__.py
kubragen2/build.py
kubragen2/configfile.py
kubragen2/data.py
kubragen2/exception.py
kubragen2/kdata.py
kubragen2/kdatahelper.py
kubragen2/kutil.py
kubragen2/merger.py
kubragen2/option.py
kubragen2/options.py
kubragen2/output.py
kubragen2/py.typed
kubragen2/util.py
kubragen2/cmd/__init__.py
kubragen2/cmd/yamltodict.py
kubragen2/private/__init__.py
kubragen2/private/merger.py
kubragen2/private/optionsmerger.py
kubragen2/provider/__init__.py
kubragen2/provider/aws.py
kubragen2/provider/azure.py
kubragen2/provider/digitalocean.py
kubragen2/provider/gcloud.py
kubragen2/tests/__init__.py
kubragen2/tests/test_build.py
kubragen2/tests/test_options.py
kubragen2/tests/test_util.py
kubragen2-0.8.7.dist-info/LICENSE
kubragen2-0.8.7.dist-info/METADATA
kubragen2-0.8.7.dist-info/WHEEL
kubragen2-0.8.7.dist-info/top_level.txt
kubragen2-0.8.7.dist-info/RECORD
