Metadata-Version: 2.1
Name: kubragen2
Version: 0.8.7
Summary: KubraGen2: programmatic Kubernetes YAML generator
Home-page: https://github.com/RangelReale/kubragen2
Author: Rangel Reale
Author-email: rangelreale@gmail.com
License: UNKNOWN
Platform: UNKNOWN
Classifier: Programming Language :: Python :: 3
Classifier: License :: OSI Approved :: MIT License
Classifier: Operating System :: OS Independent
Requires-Python: >=3.6
Requires-Dist: PyYAML (>=5.3.1)
Requires-Dist: requests (>=2.24.0)
Requires-Dist: jsonpatchext (>=1.37)
Requires-Dist: deepmerge (>=0.1)
